[
  {
    "sha": "f48767d8acca18249f81aec136bf43c7385b7321",
    "author": "jasonv47",
    "stats": {
      "additions": 9,
      "deletions": 5
    }
  },
  {
    "sha": "1452224bdd4c708f55f46ac6994828342fb6cb2a",
    "author": "jasonv47",
    "stats": {
      "additions": 138,
      "deletions": 56
    }
  },
  {
    "sha": "554f820e97088b8c86ce83a53250bdf52b222311",
    "author": "gitconzo",
    "stats": {
      "additions": 2,
      "deletions": 2
    }
  },
  {
    "sha": "5399680c62ef25667404016962d091f43cab0ba8",
    "author": "gitconzo",
    "stats": {
      "additions": 36,
      "deletions": 104
    }
  },
  {
    "sha": "7f931b42f4304f508946d88321dea42e29059ebb",
    "author": "jasonv47",
    "stats": {
      "additions": 77,
      "deletions": 11
    }
  },
  {
    "sha": "6681911bfa34d910c2af530f9077b244b92b9138",
    "author": "Kavinduwer11",
    "stats": {
      "additions": 84,
      "deletions": 49
    }
  },
  {
    "sha": "7cf6b0d7b74799e3b61a4af343fa8ffc9562c335",
    "author": "jasonv47",
    "stats": {
      "additions": 76,
      "deletions": 33
    }
  },
  {
    "sha": "55b236e4e48a606fc7b462a7ec0163163b692ade",
    "author": "Kavinduwer11",
    "stats": {
      "additions": 516,
      "deletions": 1275
    }
  },
  {
    "sha": "bd71b93abb1b375d527b7cb69a7a8d4d0c8db056",
    "author": "Kavinduwer11",
    "stats": {
      "additions": 1381,
      "deletions": 534
    }
  },
  {
    "sha": "bcf54db0ccbfaee33d31566a30fcf7d00e895b70",
    "author": "jasonv47",
    "stats": {
      "additions": 819,
      "deletions": 46
    }
  },
  {
    "sha": "d0c6c0b5d9112f261ee919befb886cada4fa7251",
    "author": "Kavinduwer11",
    "stats": {
      "additions": 792,
      "deletions": 809
    }
  },
  {
    "sha": "03b31581bbc1a3bd82aac40637a3a1f2592ae636",
    "author": "Kavinduwer11",
    "stats": {
      "additions": 1614,
      "deletions": 1073
    }
  },
  {
    "sha": "591fc6c18733d674b0a63595cf83eb9c84743a76",
    "author": "gitconzo",
    "stats": {
      "additions": 20,
      "deletions": 19
    }
  },
  {
    "sha": "ce60d0b73145c379d84f52b77802421dedd6dc04",
    "author": "gitconzo",
    "stats": {
      "additions": 3,
      "deletions": 3
    }
  },
  {
    "sha": "b1f43d4eda71586c0d42528fd2efb97d558a278a",
    "author": "gitconzo",
    "stats": {
      "additions": 442,
      "deletions": 10
    }
  },
  {
    "sha": "2b20a649aa5564ff1768c868c3174686db22f000",
    "author": "jasonv47",
    "stats": {
      "additions": 235,
      "deletions": 198
    }
  },
  {
    "sha": "cf1c54ef24b4b449fa9848504dd439e2a0b148fb",
    "author": "jasonv47",
    "stats": {
      "additions": 193,
      "deletions": 77
    }
  },
  {
    "sha": "9c3449e1a21358d0cf45d46e1bbc36f5775cbf86",
    "author": "jasonv47",
    "stats": {
      "additions": 11,
      "deletions": 4
    }
  },
  {
    "sha": "96f0bcc9c7b7e8d194a6294a5c9447fc521f239b",
    "author": "Kavinduwer11",
    "stats": {
      "additions": 67,
      "deletions": 17
    }
  },
  {
    "sha": "4702d8bf490aff18cc567ba63c15ede67d212bc1",
    "author": "gitconzo",
    "stats": {
      "additions": 288,
      "deletions": 40
    }
  },
  {
    "sha": "4f8b87192c5ec525fdbfd1b3c0e1c57aaa1bdeb5",
    "author": "gitconzo",
    "stats": {
      "additions": 31,
      "deletions": 0
    }
  },
  {
    "sha": "31427d9e6172aa6c76951fb38eb067509f8b4941",
    "author": "gitconzo",
    "stats": {
      "additions": 185,
      "deletions": 192
    }
  },
  {
    "sha": "3fedf0df223859dcdcc6e6c70c97990f28f4a4b9",
    "author": "gitconzo",
    "stats": {
      "additions": 27,
      "deletions": 4
    }
  },
  {
    "sha": "3736b5ca9a0e9e3284d6e69619cc7dd004d9bfc7",
    "author": "gitconzo",
    "stats": {
      "additions": 7,
      "deletions": 0
    }
  },
  {
    "sha": "4d1ce0ce04c36a994d5b74a194a0e20c9d6c7631",
    "author": "gitconzo",
    "stats": {
      "additions": 497,
      "deletions": 441
    }
  },
  {
    "sha": "beffb2f359bb3f7efe1324cab7bc6ddd330830de",
    "author": "jasonv47",
    "stats": {
      "additions": 10,
      "deletions": 7
    }
  },
  {
    "sha": "4ba114617f0d0fc81e9990b7f3d4a0fefdeb85fb",
    "author": "gitconzo",
    "stats": {
      "additions": 57,
      "deletions": 40
    }
  },
  {
    "sha": "081b75b87e473fbfb98b50e2042cdec4950fc91f",
    "author": "gitconzo",
    "stats": {
      "additions": 82,
      "deletions": 0
    }
  },
  {
    "sha": "9efb45648739fb55b8dd4177fd2eefe34142bcd3",
    "author": "gitconzo",
    "stats": {
      "additions": 98,
      "deletions": 145
    }
  },
  {
    "sha": "cfd11a9b8142664c32c4f4da10cd28502b007e32",
    "author": "gitconzo",
    "stats": {
      "additions": 502,
      "deletions": 147
    }
  },
  {
    "sha": "ec500b748d58a3d5473871c352cb19f777069ea6",
    "author": "gitconzo",
    "stats": {
      "additions": 295,
      "deletions": 55
    }
  },
  {
    "sha": "b2984b85a94f36a73449a828a02d4e895fb117c5",
    "author": "gitconzo",
    "stats": {
      "additions": 820,
      "deletions": 838
    }
  },
  {
    "sha": "6a88667fef97e1617fdf4259551d351dae368f15",
    "author": "gitconzo",
    "stats": {
      "additions": 78,
      "deletions": 64
    }
  },
  {
    "sha": "1814f2338f263827360a426bd85c151ade52f5e7",
    "author": "Kavinduwer11",
    "stats": {
      "additions": 288,
      "deletions": 38
    }
  },
  {
    "sha": "988e0b33b4a0bd5f39c397c44713ede988641cca",
    "author": "Kavinduwer11",
    "stats": {
      "additions": 189,
      "deletions": 70
    }
  },
  {
    "sha": "fc5f12f4a54879f94859c6d01afd758a511065a6",
    "author": "Kavinduwer11",
    "stats": {
      "additions": 442,
      "deletions": 3
    }
  },
  {
    "sha": "dfc3fabe494c08107df82648a788f47541c179ad",
    "author": "Kavinduwer11",
    "stats": {
      "additions": 589,
      "deletions": 45
    }
  },
  {
    "sha": "8bd0a3c83fb9d499e5d32767f36d90a6e61dc7e6",
    "author": "Kavinduwer11",
    "stats": {
      "additions": 379,
      "deletions": 31
    }
  },
  {
    "sha": "feca55ce87fa1b1384dfeb0a018487676098911e",
    "author": "Kavinduwer11",
    "stats": {
      "additions": 110,
      "deletions": 38
    }
  },
  {
    "sha": "3e4d5b4883d1246205edee58d6bfe4503dce8c24",
    "author": "Kavinduwer11",
    "stats": {
      "additions": 200,
      "deletions": 64
    }
  },
  {
    "sha": "32c78dbbe2438c91297e84773e18d2547f8ef1c8",
    "author": "Kavinduwer11",
    "stats": {
      "additions": 522,
      "deletions": 108
    }
  },
  {
    "sha": "c028af73072e5049b482d3f006288bd2574e539d",
    "author": "Kavinduwer11",
    "stats": {
      "additions": 1062,
      "deletions": 503
    }
  },
  {
    "sha": "7653271de41368b446996bf4e0388515b7ca050e",
    "author": "Kavinduwer11",
    "stats": {
      "additions": 380,
      "deletions": 51
    }
  },
  {
    "sha": "96f8a7528d47c2b205fcd1b8a8dd0dbd9f9357af",
    "author": "gitconzo",
    "stats": {
      "additions": 66,
      "deletions": 55
    }
  },
  {
    "sha": "d553c9dd8a471cc17890835eb090cbccda053a14",
    "author": "gitconzo",
    "stats": {
      "additions": 23,
      "deletions": 9
    }
  },
  {
    "sha": "9d4d03a54b4533a38d89cf654ff89d0589f017a0",
    "author": "gitconzo",
    "stats": {
      "additions": 0,
      "deletions": 0
    }
  },
  {
    "sha": "b2a6dee56f150d9885cf1e98ba6b66fbb2b03da9",
    "author": "gitconzo",
    "stats": {
      "additions": 0,
      "deletions": 1
    }
  },
  {
    "sha": "8b1b458b00656f4bda9550c0964bf9459b57889d",
    "author": "gitconzo",
    "stats": {
      "additions": 620,
      "deletions": 456
    }
  },
  {
    "sha": "e935e698d6322f07b5ed7200bbb9b711652df226",
    "author": "gitconzo",
    "stats": {
      "additions": 61,
      "deletions": 39
    }
  },
  {
    "sha": "e1ab1f9388969cb344b0d6b4b535c98c9fe89601",
    "author": "gitconzo",
    "stats": {
      "additions": 2598,
      "deletions": 1043
    }
  },
  {
    "sha": "a50f3bbe35117084513396863771f0d32bcd8e55",
    "author": "gitconzo",
    "stats": {
      "additions": 252,
      "deletions": 78
    }
  },
  {
    "sha": "bcdb56e0a574e44926f96c688824d819ec69fc8a",
    "author": "gitconzo",
    "stats": {
      "additions": 34,
      "deletions": 31
    }
  },
  {
    "sha": "ec6c7832e0c1d3644d06fb030aa567e513d0b68b",
    "author": "gitconzo",
    "stats": {
      "additions": 5,
      "deletions": 4
    }
  },
  {
    "sha": "7906ae4283aec40f3f5f37f4ae41c84b4dfd6135",
    "author": "gitconzo",
    "stats": {
      "additions": 304,
      "deletions": 201
    }
  },
  {
    "sha": "4324a30cbbc3165770949c873e76defa97130357",
    "author": "gitconzo",
    "stats": {
      "additions": 145,
      "deletions": 58
    }
  },
  {
    "sha": "f5df5f0ea4b8cadc9858372af3cc4319f1cfa354",
    "author": "gitconzo",
    "stats": {
      "additions": 19,
      "deletions": 0
    }
  },
  {
    "sha": "d57ac1dbdf5b42179ea3e5754bfe2da9655899a8",
    "author": "gitconzo",
    "stats": {
      "additions": 0,
      "deletions": 0
    }
  },
  {
    "sha": "187c1495e6a062768acd0b1d7bb0a313e8497547",
    "author": "jasonv47",
    "stats": {
      "additions": 429,
      "deletions": 99
    }
  },
  {
    "sha": "82a5b1b5f17e111ea7f65b5b87c226ec826e7dfa",
    "author": "gitconzo",
    "stats": {
      "additions": 207,
      "deletions": 0
    }
  },
  {
    "sha": "c6b51318d768998c8c3b9ab88eb5dc7f0bc3b438",
    "author": "gitconzo",
    "stats": {
      "additions": 8,
      "deletions": 8
    }
  },
  {
    "sha": "ca8077c20e50a8d01683d6c7f9af9c8689298f66",
    "author": "Kavinduwer11",
    "stats": {
      "additions": 2602,
      "deletions": 163
    }
  },
  {
    "sha": "b795124db7276d6a31d719e0acbb0b726244bc45",
    "author": "jasonv47",
    "stats": {
      "additions": 285,
      "deletions": 209
    }
  },
  {
    "sha": "49dc504bf6a0737c64addfe579ed1e3dae98fcaa",
    "author": "gitconzo",
    "stats": {
      "additions": 0,
      "deletions": 0
    }
  },
  {
    "sha": "f24df3a23837b4ae37a6d831411518f9f9cad290",
    "author": "gitconzo",
    "stats": {
      "additions": 0,
      "deletions": 0
    }
  },
  {
    "sha": "3543745c9d8f89ed365b9ff6ed51a7b9c0d83378",
    "author": "gitconzo",
    "stats": {
      "additions": 2,
      "deletions": 2
    }
  },
  {
    "sha": "1427575ab8b0cb274b36eec369f31ba03811e10f",
    "author": "gitconzo",
    "stats": {
      "additions": 0,
      "deletions": 33
    }
  },
  {
    "sha": "d9168da7982cde0f17576539bff4b7a9a0b41acf",
    "author": "gitconzo",
    "stats": {
      "additions": 616,
      "deletions": 888
    }
  },
  {
    "sha": "7a85bed938358a0f0511c89fd7fb1d6431fdcbf3",
    "author": "gitconzo",
    "stats": {
      "additions": 0,
      "deletions": 0
    }
  },
  {
    "sha": "3719c61371c4a7aff08f712e5cbcb26ce9064e50",
    "author": "jasonv47",
    "stats": {
      "additions": 242,
      "deletions": 61
    }
  },
  {
    "sha": "44db1e1f3225cdd016d184b71e49287c7f469d5b",
    "author": "gitconzo",
    "stats": {
      "additions": 196,
      "deletions": 165
    }
  },
  {
    "sha": "06570dfee4a7bbca4083806897a5a318523427a3",
    "author": "gitconzo",
    "stats": {
      "additions": 79,
      "deletions": 200
    }
  },
  {
    "sha": "e6207a9869ac96746b80441c0125a10ba629aa68",
    "author": "gitconzo",
    "stats": {
      "additions": 692,
      "deletions": 227
    }
  },
  {
    "sha": "1c1eb7757615226a4efab4323278afb6c5b0ef33",
    "author": "jasonv47",
    "stats": {
      "additions": 4,
      "deletions": 4
    }
  },
  {
    "sha": "b7f665efa1c6a5cf516ca72cd69d4493266b96e6",
    "author": "gitconzo",
    "stats": {
      "additions": 149,
      "deletions": 115
    }
  },
  {
    "sha": "cb4b87a1864f8cf6cdf4a8fb21189f6782643a01",
    "author": "gitconzo",
    "stats": {
      "additions": 115,
      "deletions": 28
    }
  },
  {
    "sha": "9c1304b42e2be52becdd171a78d7d0fc6c53693d",
    "author": "gitconzo",
    "stats": {
      "additions": 97,
      "deletions": 41
    }
  },
  {
    "sha": "0e377451289962744da4a41bd433cf453a24b632",
    "author": "gitconzo",
    "stats": {
      "additions": 228,
      "deletions": 121
    }
  },
  {
    "sha": "37d44ffa0f5e2fcde12bc2dc6b101119d829ec20",
    "author": "gitconzo",
    "stats": {
      "additions": 2492,
      "deletions": 1134
    }
  },
  {
    "sha": "428501e2acfb9123cc1ec69defbca81f948f9724",
    "author": "Kavinduwer11",
    "stats": {
      "additions": 320,
      "deletions": 3
    }
  },
  {
    "sha": "a5765e4f4778cb8da2ae435e5fb253b8fa4adda7",
    "author": "gitconzo",
    "stats": {
      "additions": 449,
      "deletions": 181
    }
  },
  {
    "sha": "1708d8cd995554dd1255a1709de162b412ca8c30",
    "author": "jasonv47",
    "stats": {
      "additions": 444,
      "deletions": 30
    }
  },
  {
    "sha": "ebd15f1f577c4f4d5493416a5c65c56e7dca31a4",
    "author": "gitconzo",
    "stats": {
      "additions": 741,
      "deletions": 388
    }
  },
  {
    "sha": "8f40626e30c1d89eb4704725596d352baf45bcc5",
    "author": "gitconzo",
    "stats": {
      "additions": 142,
      "deletions": 4
    }
  },
  {
    "sha": "a445facdbe0a977bf16bd98dcc3a5a178c550a8f",
    "author": "gitconzo",
    "stats": {
      "additions": 48,
      "deletions": 177
    }
  },
  {
    "sha": "14976ffee2a53aafae868069e31c21ffb821d494",
    "author": "gitconzo",
    "stats": {
      "additions": 1198,
      "deletions": 81
    }
  },
  {
    "sha": "19443cea5a6f0ff6145efb022e9727827683de9d",
    "author": "urjenz",
    "stats": {
      "additions": 0,
      "deletions": 0
    }
  },
  {
    "sha": "51078192f256de91b7b689cd76a6ff1d3becbb45",
    "author": "gitconzo",
    "stats": {
      "additions": 53,
      "deletions": 13
    }
  },
  {
    "sha": "b5ccc28a2dd0488bfed47ade7622011b8d589a3a",
    "author": "gitconzo",
    "stats": {
      "additions": 37,
      "deletions": 6
    }
  },
  {
    "sha": "f397a20b64e186d2088ecb71efc3f45b0fbc65f5",
    "author": "gitconzo",
    "stats": {
      "additions": 81,
      "deletions": 15
    }
  },
  {
    "sha": "4ceb8cf47a7fe714f64541478d8392d963792c24",
    "author": "gitconzo",
    "stats": {
      "additions": 1,
      "deletions": 0
    }
  },
  {
    "sha": "a909faa3e36f27ceaad8121b1b967def01c29d83",
    "author": "gitconzo",
    "stats": {
      "additions": 39,
      "deletions": 24
    }
  },
  {
    "sha": "761b35d460963eb6c69a3aed0549cb3422eb5474",
    "author": "gitconzo",
    "stats": {
      "additions": 264,
      "deletions": 0
    }
  },
  {
    "sha": "30b78f6ba9870321901979a7342040ca8a055157",
    "author": "urjenz",
    "stats": {
      "additions": 157,
      "deletions": 265
    }
  },
  {
    "sha": "986ee32930053b3bfa20bb73a940d019f248aa14",
    "author": "urjenz",
    "stats": {
      "additions": 10,
      "deletions": 10
    }
  },
  {
    "sha": "1b284c5171462bf188b88a294d6d8a58278d44bd",
    "author": "urjenz",
    "stats": {
      "additions": 108,
      "deletions": 45
    }
  },
  {
    "sha": "ebc117518e49939c71502ab1fed198e3c1fcbdce",
    "author": "urjenz",
    "stats": {
      "additions": 2127,
      "deletions": 330
    }
  },
  {
    "sha": "1073ae9e4748b00514b8ff73f4a869bc3ca2d575",
    "author": "jasonv47",
    "stats": {
      "additions": 140,
      "deletions": 46
    }
  },
  {
    "sha": "8313e20ccd37ae858b765d54e5861d3ddef4f080",
    "author": "gitconzo",
    "stats": {
      "additions": 196,
      "deletions": 22
    }
  },
  {
    "sha": "3aca9f290d2d8a842a2b34fe1e2dd9d399436d67",
    "author": "gitconzo",
    "stats": {
      "additions": 76,
      "deletions": 27
    }
  },
  {
    "sha": "63bf18359f6de6c57d1df5028067a96f3400befe",
    "author": "gitconzo",
    "stats": {
      "additions": 28,
      "deletions": 108
    }
  },
  {
    "sha": "c30e4dd658c4ebbbcf321b5c87f6b18541e61ef1",
    "author": "gitconzo",
    "stats": {
      "additions": 0,
      "deletions": 3
    }
  },
  {
    "sha": "a99963445c8626d572a4df1eaaedc44dbb2bc269",
    "author": "gitconzo",
    "stats": {
      "additions": 2,
      "deletions": 2
    }
  },
  {
    "sha": "84457afd07308678e6227aff8bb845c08c045355",
    "author": "gitconzo",
    "stats": {
      "additions": 0,
      "deletions": 1
    }
  },
  {
    "sha": "a73715a6452cc0b37875a83a2d90cf67e19992c3",
    "author": "gitconzo",
    "stats": {
      "additions": 27,
      "deletions": 2
    }
  },
  {
    "sha": "54fe2209af2b77f607fcea4ace908047d16a2a67",
    "author": "gitconzo",
    "stats": {
      "additions": 21,
      "deletions": 8
    }
  },
  {
    "sha": "868cb3b84ef9fc3aa89d91e5c968a09d6b4c18aa",
    "author": "gitconzo",
    "stats": {
      "additions": 137,
      "deletions": 76
    }
  },
  {
    "sha": "5c9fdd2adce3b05ae2203b50e6134350e39f1a82",
    "author": "gitconzo",
    "stats": {
      "additions": 17,
      "deletions": 467
    }
  },
  {
    "sha": "714bfbe111419ad90d8fff059e643be61414ccd5",
    "author": "gitconzo",
    "stats": {
      "additions": 886,
      "deletions": 124
    }
  },
  {
    "sha": "65624e94c54780d34005b0a54170882990243ffb",
    "author": "jasonv47",
    "stats": {
      "additions": 281,
      "deletions": 57
    }
  },
  {
    "sha": "2c13a0166569e05a427f300b5790097a812152a5",
    "author": "jasonv47",
    "stats": {
      "additions": 387,
      "deletions": 127
    }
  },
  {
    "sha": "8735b4d0fd2383f88eccd9a3530e24e30b1f5dc6",
    "author": "jasonv47",
    "stats": {
      "additions": 413,
      "deletions": 58
    }
  },
  {
    "sha": "18268a54d562401f18f9dbe0538e9b9fef71c11f",
    "author": "jasonv47",
    "stats": {
      "additions": 10,
      "deletions": 7
    }
  },
  {
    "sha": "c19acf8e73717c70245b54fe18d66032531a8f65",
    "author": "jasonv47",
    "stats": {
      "additions": 47,
      "deletions": 0
    }
  },
  {
    "sha": "053665eb65310c5a604796a92028097a7a12d2a1",
    "author": "jasonv47",
    "stats": {
      "additions": 35,
      "deletions": 0
    }
  },
  {
    "sha": "a035036208470c0ee5bbcd3ff8ba7d20030dc002",
    "author": "jasonv47",
    "stats": {
      "additions": 60,
      "deletions": 11
    }
  },
  {
    "sha": "d45addcdae260cd0d4bbadb126909229f254bcc9",
    "author": "jasonv47",
    "stats": {
      "additions": 199,
      "deletions": 3
    }
  },
  {
    "sha": "467cb2a34c02604ff915e4055e165bcd565dabb6",
    "author": "jasonv47",
    "stats": {
      "additions": 295,
      "deletions": 55
    }
  },
  {
    "sha": "fa15d07a58740c72410700295941134e4005c5bc",
    "author": "Kavinduwer11",
    "stats": {
      "additions": 1215,
      "deletions": 285
    }
  },
  {
    "sha": "acfc1b3622d182ee286100f379ccb962d4654b4c",
    "author": "urjenz",
    "stats": {
      "additions": 85,
      "deletions": 21
    }
  },
  {
    "sha": "b26c31005b1b1ec1245d1cb014fc09a89904de09",
    "author": "urjenz",
    "stats": {
      "additions": 156,
      "deletions": 23
    }
  },
  {
    "sha": "61b32417e500ec4790955f84112f4357194b775c",
    "author": "urjenz",
    "stats": {
      "additions": 0,
      "deletions": 0
    }
  },
  {
    "sha": "646f83769482fba963a2374bea6fb0d4dc40b8c8",
    "author": "jasonv47",
    "stats": {
      "additions": 13,
      "deletions": 10
    }
  },
  {
    "sha": "ba4e81f14c13e0bc29e647f4ef0f5afe0ac3545b",
    "author": "urjenz",
    "stats": {
      "additions": 48,
      "deletions": 12
    }
  },
  {
    "sha": "031d4a0d06c342f8c0a542b4658370d55aa2fef5",
    "author": "urjenz",
    "stats": {
      "additions": 10,
      "deletions": 48
    }
  },
  {
    "sha": "e9aa1063d13a598b09f35368c99ef8a5ea54e234",
    "author": "urjenz",
    "stats": {
      "additions": 48,
      "deletions": 6
    }
  },
  {
    "sha": "15539787e6318d2150cfdf37dc8256d1e5f15634",
    "author": "urjenz",
    "stats": {
      "additions": 391,
      "deletions": 0
    }
  },
  {
    "sha": "6d392bc3a70f762ceed16076070409cc3b22e78e",
    "author": "urjenz",
    "stats": {
      "additions": 168,
      "deletions": 0
    }
  },
  {
    "sha": "f6355b78cf714588bc8f0e5d9fbdab2535acc346",
    "author": "urjenz",
    "stats": {
      "additions": 503,
      "deletions": 0
    }
  },
  {
    "sha": "9625f0945bfc8340339a25afe7063f8503d5f0bd",
    "author": "urjenz",
    "stats": {
      "additions": 202,
      "deletions": 0
    }
  },
  {
    "sha": "d956a1b689a9ba6126be650315c48d6e0a507318",
    "author": "urjenz",
    "stats": {
      "additions": 698,
      "deletions": 27
    }
  },
  {
    "sha": "dd6033eb7764aa761c18824fe605f7ff94979892",
    "author": "Kavinduwer11",
    "stats": {
      "additions": 217,
      "deletions": 30
    }
  },
  {
    "sha": "cb1220ba7e4329187545c471f2caf28cfad35639",
    "author": "jasonv47",
    "stats": {
      "additions": 953,
      "deletions": 31
    }
  },
  {
    "sha": "54a4626dd1b097d98ff6a4a5c3e32e1c77de6562",
    "author": "jasonv47",
    "stats": {
      "additions": 85,
      "deletions": 10
    }
  }
]